Workbook

Sheet Read me
A1: KM Claims - Step 4 vs Step 5 (REAL data, interactive)
A4: Populated from your real step-4 and step-5 output files.
A6: Sheets per entity: Ratings (editable) | Summary (live kappa) | Disagree (review list).
A8: Edit a rating in a Ratings sheet and the matching Summary sheet updates live.
A10: Claimants: 1990 entities, 263 disagreements to review
A11: Dealers: 225 entities, 31 disagreements to review

Sheet Claimants
A1: Claimants - Step 4 vs Step 5 (editable)
A2: Change the Step 4 / Step 5 columns; the Summary sheet updates live.
A4: ClaimantName | B4: claim_count | C4: high_count | D4: raw_high_rate | E4: wilson_lower | F4: step4_level | G4: step5_level | H4: agree?
A5: Aaron Bowman | B5: 3 | C5: 3 | D5: 1 | E5: 0.4385 | F5: High | G5: High | H5: =IF(F5=G5,"YES","NO")
A6: Aaron Piper | B6: 33 | C6: 8 | D6: 0.2424 | E6: 0.1283 | F6: High | G6: High | H6: =IF(F6=G6,"YES","NO")
A7: Adam Allen | B7: 285 | C7: 81 | D7: 0.2842 | E7: 0.235 | F7: High | G7: Low | H7: =IF(F7=G7,"YES","NO")
A8: Adam Jack | B8: 532 | C8: 113 | D8: 0.2124 | E8: 0.1798 | F8: High | G8: High | H8: =IF(F8=G8,"YES","NO")
A9: Alan Walker | B9: 83 | C9: 19 | D9: 0.2289 | E9: 0.1517 | F9: High | G9: High | H9: =IF(F9=G9,"YES","NO")
A10: Alec Houser | B10: 716 | C10: 107 | D10: 0.1494 | E10: 0.1252 | F10: High | G10: Low | H10: =IF(F10=G10,"YES","NO")
A11: Alex McClung | B11: 4 | C11: 3 | D11: 0.75 | E11: 0.3006 | F11: High | G11: Medium | H11: =IF(F11=G11,"YES","NO")
A12: Alex Smagala | B12: 377 | C12: 231 | D12: 0.6127 | E12: 0.5627 | F12: High | G12: High | H12: =IF(F12=G12,"YES","NO")
A13: Allie Reece | B13: 1 | C13: 1 | D13: 1 | E13: 0.2065 | F13: High | G13: Low | H13: =IF(F13=G13,"YES","NO")
A14: Alyssa Cline | B14: 105 | C14: 73 | D14: 0.6952 | E14: 0.6016 | F14: High | G14: High | H14: =IF(F14=G14,"YES","NO")
A15: Amy Echols | B15: 11 | C15: 7 | D15: 0.6364 | E15: 0.3538 | F15: High | G15: High | H15: =IF(F15=G15,"YES","NO")
A16: Amy Lagaras | B16: 36 | C16: 15 | D16: 0.4167 | E16: 0.2714 | F16: High | G16: High | H16: =IF(F16=G16,"YES","NO")
... A1994: Zachary Schechter | B1994: 2 | C1994: 1 | D1994: 0.5 | E1994: 0.0945 | F1994: Medium | G1994: Medium | H1994: =IF(F1994=G1994,"YES","NO")

Sheet Summary (Claimants)
A1: Comparison Summary - Claimants (recalculates live)
A3: Total | B3: =COUNTA('Claimants'!$F$5:$F$1994)
A4: Exact agreement (count) | B4: =SUMPRODUCT(--('Claimants'!$F$5:$F$1994='Claimants'!$G$5:$G$1994))
A5: Exact agreement (%) | B5: =B4/B3
A7: Agreement matrix (rows = Step 4, cols = Step 5)
B8: High | C8: Medium | D8: Low
A9: High | B9: =SUMPRODUCT(--('Claimants'!$F$5:$F$1994="High"),--('Claimants'!$G$5:$G$1994="High")) | C9: =SUMPRODUCT(--('Claimants'!$F$5:$F$1994="High"),--('Claimants'!$G$5:$G$1994="Medium")) | D9: =SUMPRODUCT(--('Claimants'!$F$5:$F$1994="High"),--('Claimants'!$G$5:$G$1994="Low")) | E9: =SUM(B9:D9)
A10: Medium | B10: =SUMPRODUCT(--('Claimants'!$F$5:$F$1994="Medium"),--('Claimants'!$G$5:$G$1994="High")) | C10: =SUMPRODUCT(--('Claimants'!$F$5:$F$1994="Medium"),--('Claimants'!$G$5:$G$1994="Medium")) | D10: =SUMPRODUCT(--('Claimants'!$F$5:$F$1994="Medium"),--('Claimants'!$G$5:$G$1994="Low")) | E10: =SUM(B10:D10)
A11: Low | B11: =SUMPRODUCT(--('Claimants'!$F$5:$F$1994="Low"),--('Claimants'!$G$5:$G$1994="High")) | C11: =SUMPRODUCT(--('Claimants'!$F$5:$F$1994="Low"),--('Claimants'!$G$5:$G$1994="Medium")) | D11: =SUMPRODUCT(--('Claimants'!$F$5:$F$1994="Low"),--('Claimants'!$G$5:$G$1994="Low")) | E11: =SUM(B11:D11)
B12: =SUM(B9:B11) | C12: =SUM(C9:C11) | D12: =SUM(D9:D11)
A14: Cohen's kappa (agreement beyond chance)
A15: po (observed) | B15: =B5
A16: pe (expected) | B16: =(E9*B12+E10*C12+E11*D12)/(B3*B3)
A17: kappa | B17: =(B15-B16)/(1-B16)
A18: Interpretation | B18: =IF(B17<0,"worse than chance",IF(B17<=0.2,"slight",IF(B17<=0.4,"fair",IF(B17<=0.6,"moderate",IF(B17<=0.8,"substantial","almost perfect")))))

Sheet Disagree (Claimants)
A1: Disagreements - Claimants (review priority)
A3: ClaimantName | B3: claim_count | C3: high_count | D3: raw_high_rate | E3: wilson_lower | F3: step4_level | G3: step5_level
A4: Adam Allen | B4: 285 | C4: 81 | D4: 0.2842 | E4: 0.235 | F4: High | G4: Low
A5: Alec Houser | B5: 716 | C5: 107 | D5: 0.1494 | E5: 0.1252 | F5: High | G5: Low
A6: Alex McClung | B6: 4 | C6: 3 | D6: 0.75 | E6: 0.3006 | F6: High | G6: Medium
A7: Allie Reece | B7: 1 | C7: 1 | D7: 1 | E7: 0.2065 | F7: High | G7: Low
A8: Andre Stone | B8: 2 | C8: 2 | D8: 1 | E8: 0.3424 | F8: High | G8: Medium
A9: Ariana Nino | B9: 10 | C9: 6 | D9: 0.6 | E9: 0.3127 | F9: High | G9: Low
A10: Bo Turbeville | B10: 12 | C10: 9 | D10: 0.75 | E10: 0.4677 | F10: High | G10: Medium
A11: Bob Murphy | B11: 36 | C11: 12 | D11: 0.3333 | E11: 0.2021 | F11: High | G11: Low
A12: Bob McGowan | B12: 37 | C12: 9 | D12: 0.2432 | E12: 0.1336 | F12: High | G12: Low
A13: Brad Gerber | B13: 77 | C13: 20 | D13: 0.2597 | E13: 0.1749 | F13: High | G13: Low
A14: Brenda Wall | B14: 4 | C14: 2 | D14: 0.5 | E14: 0.15 | F14: High | G14: Medium
A15: Carl Dunaway | B15: 12 | C15: 4 | D15: 0.3333 | E15: 0.1381 | F15: High | G15: Medium
... A266: Walker Marlowe | B266: 4 | C266: 1 | D266: 0.25 | E266: 0.0456 | F266: Medium | G266: High

Sheet Dealers
A1: Dealers - Step 4 vs Step 5 (editable)
A2: Change the Step 4 / Step 5 columns; the Summary sheet updates live.
A4: DealerName | B4: claim_count | C4: high_count | D4: raw_high_rate | E4: wilson_lower | F4: step4_level | G4: step5_level | H4: agree?
A5: ATHENS DIGITAL SYSTEMS, INC. | B5: 18 | C5: 7 | D5: 0.3889 | E5: 0.203 | F5: High | G5: High | H5: =IF(F5=G5,"YES","NO")
A6: BORING BUSINESS SYSTEMS, INC. | B6: 493 | C6: 112 | D6: 0.2272 | E6: 0.1924 | F6: High | G6: High | H6: =IF(F6=G6,"YES","NO")
A7: COPITEX BUSINESS MACHINES | B7: 1 | C7: 1 | D7: 1 | E7: 0.2065 | F7: High | G7: High | H7: =IF(F7=G7,"YES","NO")
A8: Commercial Print | B8: 2 | C8: 2 | D8: 1 | E8: 0.3424 | F8: High | G8: Medium | H8: =IF(F8=G8,"YES","NO")
A9: DBA DIGITAL SERVICE & SALES | B9: 421 | C9: 276 | D9: 0.6556 | E9: 0.609 | F9: High | G9: High | H9: =IF(F9=G9,"YES","NO")
A10: DBA FLEXTG - HQ | B10: 3644 | C10: 634 | D10: 0.174 | E10: 0.162 | F10: High | G10: High | H10: =IF(F10=G10,"YES","NO")
A11: DBA MERIDIAN IMAGING SOLUTIONS | B11: 10 | C11: 10 | D11: 1 | E11: 0.7225 | F11: High | G11: High | H11: =IF(F11=G11,"YES","NO")
A12: DBA NEW YORK BUSINESS SYSTEMS | B12: 394 | C12: 125 | D12: 0.3173 | E12: 0.2733 | F12: High | G12: High | H12: =IF(F12=G12,"YES","NO")
A13: DBA NOVATECH- DALLAS | B13: 991 | C13: 400 | D13: 0.4036 | E13: 0.3735 | F13: High | G13: High | H13: =IF(F13=G13,"YES","NO")
A14: DBA NOVATECH-MEMPHIS | B14: 6235 | C14: 848 | D14: 0.136 | E14: 0.1277 | F14: High | G14: High | H14: =IF(F14=G14,"YES","NO")
A15: DBA PROSOURCE | B15: 4039 | C15: 535 | D15: 0.1325 | E15: 0.1224 | F15: High | G15: Low | H15: =IF(F15=G15,"YES","NO")
A16: DBA REGAL BUSINESS MACHINE COMPANY | B16: 1151 | C16: 285 | D16: 0.2476 | E16: 0.2235 | F16: High | G16: High | H16: =IF(F16=G16,"YES","NO")
... A229: OFFICECORP, INC. | B229: 10 | C229: 3 | D229: 0.3 | E229: 0.1078 | F229: Medium | G229: Medium | H229: =IF(F229=G229,"YES","NO")

Sheet Summary (Dealers)
A1: Comparison Summary - Dealers (recalculates live)
A3: Total | B3: =COUNTA('Dealers'!$F$5:$F$229)
A4: Exact agreement (count) | B4: =SUMPRODUCT(--('Dealers'!$F$5:$F$229='Dealers'!$G$5:$G$229))
A5: Exact agreement (%) | B5: =B4/B3
A7: Agreement matrix (rows = Step 4, cols = Step 5)
B8: High | C8: Medium | D8: Low
A9: High | B9: =SUMPRODUCT(--('Dealers'!$F$5:$F$229="High"),--('Dealers'!$G$5:$G$229="High")) | C9: =SUMPRODUCT(--('Dealers'!$F$5:$F$229="High"),--('Dealers'!$G$5:$G$229="Medium")) | D9: =SUMPRODUCT(--('Dealers'!$F$5:$F$229="High"),--('Dealers'!$G$5:$G$229="Low")) | E9: =SUM(B9:D9)
A10: Medium | B10: =SUMPRODUCT(--('Dealers'!$F$5:$F$229="Medium"),--('Dealers'!$G$5:$G$229="High")) | C10: =SUMPRODUCT(--('Dealers'!$F$5:$F$229="Medium"),--('Dealers'!$G$5:$G$229="Medium")) | D10: =SUMPRODUCT(--('Dealers'!$F$5:$F$229="Medium"),--('Dealers'!$G$5:$G$229="Low")) | E10: =SUM(B10:D10)
A11: Low | B11: =SUMPRODUCT(--('Dealers'!$F$5:$F$229="Low"),--('Dealers'!$G$5:$G$229="High")) | C11: =SUMPRODUCT(--('Dealers'!$F$5:$F$229="Low"),--('Dealers'!$G$5:$G$229="Medium")) | D11: =SUMPRODUCT(--('Dealers'!$F$5:$F$229="Low"),--('Dealers'!$G$5:$G$229="Low")) | E11: =SUM(B11:D11)
B12: =SUM(B9:B11) | C12: =SUM(C9:C11) | D12: =SUM(D9:D11)
A14: Cohen's kappa (agreement beyond chance)
A15: po (observed) | B15: =B5
A16: pe (expected) | B16: =(E9*B12+E10*C12+E11*D12)/(B3*B3)
A17: kappa | B17: =(B15-B16)/(1-B16)
A18: Interpretation | B18: =IF(B17<0,"worse than chance",IF(B17<=0.2,"slight",IF(B17<=0.4,"fair",IF(B17<=0.6,"moderate",IF(B17<=0.8,"substantial","almost perfect")))))

Sheet Disagree (Dealers)
A1: Disagreements - Dealers (review priority)
A3: DealerName | B3: claim_count | C3: high_count | D3: raw_high_rate | E3: wilson_lower | F3: step4_level | G3: step5_level
A4: Commercial Print | B4: 2 | C4: 2 | D4: 1 | E4: 0.3424 | F4: High | G4: Medium
A5: DBA PROSOURCE | B5: 4039 | C5: 535 | D5: 0.1325 | E5: 0.1224 | F5: High | G5: Low
A6: DBA WILSON OFFICE SOLUTIONS | B6: 5 | C6: 2 | D6: 0.4 | E6: 0.1176 | F6: High | G6: Low
A7: EXECUTIVE COLOR SYSTEMS, INC. | B7: 845 | C7: 148 | D7: 0.1751 | E7: 0.151 | F7: High | G7: Low
A8: INTEGRATED DIGITAL SOLUTIONS, INC. | B8: 8 | C8: 3 | D8: 0.375 | E8: 0.1368 | F8: High | G8: Low
A9: Mid-Atlantic | B9: 37 | C9: 10 | D9: 0.2703 | E9: 0.154 | F9: High | G9: Low
A10: Mid-South | B10: 9 | C10: 3 | D10: 0.3333 | E10: 0.1206 | F10: High | G10: Medium
A11: NATIONAL OFFICE PRODUCTS & PRINTING, INC. | B11: 132 | C11: 27 | D11: 0.2045 | E11: 0.1446 | F11: High | G11: Low
A12: NORTHERN BUSINESS MACHINES NH, INC. | B12: 5 | C12: 2 | D12: 0.4 | E12: 0.1176 | F12: High | G12: Low
A13: PANAMA BUSINESS MACHINES, INC. | B13: 29 | C13: 7 | D13: 0.2414 | E13: 0.1222 | F13: High | G13: Low
A14: PROFESSIONAL BUSINESS SYSTEMS, INC. | B14: 7 | C14: 4 | D14: 0.5714 | E14: 0.2505 | F14: High | G14: Medium
A15: RECOGNITION SYSTEMS, INC. | B15: 15 | C15: 5 | D15: 0.3333 | E15: 0.1518 | F15: High | G15: Medium
... A34: MARCO TECHNOLOGIES, LLC | B34: 71 | C34: 13 | D34: 0.1831 | E34: 0.1102 | F34: Medium | G34: High
